beeminder_client/__init__.py
beeminder_client/beeminder.py
beeminder_client/beeminder_cli.py
beeminder_client/models.py
beeminder_client-0.1.5.dist-info/LICENSE
beeminder_client-0.1.5.dist-info/METADATA
beeminder_client-0.1.5.dist-info/WHEEL
beeminder_client-0.1.5.dist-info/entry_points.txt
beeminder_client-0.1.5.dist-info/top_level.txt
beeminder_client-0.1.5.dist-info/RECORD
