Metadata-Version: 2.1
Name: beeminder-client
Version: 0.1.5
Summary: A Python client library and terminal interface for Beeminder
Home-page: https://github.com/ianm199/beeminder_api_client
Author: Your Name
Author-email: your.email@example.com
Project-URL: Bug Tracker, https://github.com/ianm199/beeminder_api_client/issues
Classifier: Programming Language :: Python :: 3
Classifier: Programming Language :: Python :: 3.8
Classifier: Programming Language :: Python :: 3.9
Classifier: Programming Language :: Python :: 3.10
Classifier: Programming Language :: Python :: 3.11
Classifier: Programming Language :: Python :: 3.12
Classifier: Programming Language :: Python :: 3.13
Classifier: License :: OSI Approved :: MIT License
Classifier: Operating System :: OS Independent
Classifier: Development Status :: 3 - Alpha
Classifier: Intended Audience :: Developers
Classifier: Topic :: Office/Business :: Financial :: Accounting
Requires-Python: >=3.8
License-File: LICENSE
Requires-Dist: requests>=2.25.1
Requires-Dist: pydantic>=2.0.0
Requires-Dist: windows-curses; platform_system == "Windows"
